README.md
whisper_cpp_cdll/__init__.py
whisper_cpp_cdll/core.py
whisper_cpp_cdll/types.py
whisper_cpp_cdll/util.py
whisper_cpp_cdll-0.0.5.dist-info/WHEEL
whisper_cpp_cdll-0.0.5.dist-info/METADATA
whisper_cpp_cdll-0.0.5.dist-info/RECORD
